wd_test_pkg/__init__.py
wd_test_pypi-0.0.1.dist-info/LICENSE
wd_test_pypi-0.0.1.dist-info/METADATA
wd_test_pypi-0.0.1.dist-info/WHEEL
wd_test_pypi-0.0.1.dist-info/top_level.txt
wd_test_pypi-0.0.1.dist-info/RECORD
