Metadata-Version: 2.1
Name: wd_test_pypi
Version: 0.0.1
Summary: test publish
Home-page: 
Author: wd
Author-email: 296525335@qq.com
License: UNKNOWN
Platform: UNKNOWN
Classifier: Programming Language :: Python :: 3
Classifier: License :: OSI Approved :: MIT License
Classifier: Operating System :: OS Independent
License-File: LICENSE
